{
  "uuid": "270ff407-50c0-4301-81f9-25e5c62d8cb3",
  "name": "Saby_ИспользоватьКЭДО",
  "name2": {
    "ru": "Saby использовать КЭДО"
  },
  "comment": "",
  "h1_0": "1",
  "h0": "3",
  "h5": [
    "0",
    "0",
    "00000000-0000-0000-0000-000000000000",
    "0"
  ],
  "data": [
    [
      "1",
      [
        "2",
        [
          "3",
          [
            "1",
            "0",
            "270ff407-50c0-4301-81f9-25e5c62d8cb3"
          ],
          "\"Saby_ИспользоватьКЭДО\"",
          [
            "1",
            "\"ru\"",
            "\"Saby использовать КЭДО\""
          ],
          "\"\"",
          "0",
          "0",
          "00000000-0000-0000-0000-000000000000",
          "0"
        ],
        "528d73e6-9957-4804-97d7-e16fc64d51ab",
        [
          "0",
          "0"
        ],
        "1"
      ],
      "0"
    ]
  ]
}