[
  {
    "name": "Saby_Комментарий",
    "raw": [
      "9",
      [
        "1"
      ],
      "0",
      "\"Saby_Комментарий\"",
      [
        "1",
        "1",
        [
          "\"ru\"",
          "\"Комментарий\""
        ]
      ],
      [
        "\"Pattern\"",
        [
          "\"S\""
        ]
      ],
      [
        "0",
        [
          "0",
          [
            "\"B\"",
            "1"
          ],
          "0"
        ]
      ],
      [
        "0",
        [
          "0",
          [
            "\"B\"",
            "1"
          ],
          "0"
        ]
      ],
      [
        "0",
        "0"
      ],
      [
        "0",
        "0"
      ],
      "0",
      "0",
      "0",
      "0",
      [
        "0",
        "0"
      ],
      [
        "0",
        "0"
      ]
    ]
  },
  {
    "name": "Saby_ФИО",
    "raw": [
      "9",
      [
        "2"
      ],
      "0",
      "\"Saby_ФИО\"",
      [
        "1",
        "1",
        [
          "\"ru\"",
          "\"Saby ФИО\""
        ]
      ],
      [
        "\"Pattern\"",
        [
          "\"S\"",
          "1",
          "1"
        ]
      ],
      [
        "0",
        [
          "0",
          [
            "\"B\"",
            "1"
          ],
          "0"
        ]
      ],
      [
        "0",
        [
          "0",
          [
            "\"B\"",
            "1"
          ],
          "0"
        ]
      ],
      [
        "0",
        "0"
      ],
      [
        "0",
        "0"
      ],
      "0",
      "0",
      "0",
      "0",
      [
        "0",
        "0"
      ],
      [
        "0",
        "0"
      ]
    ]
  },
  {
    "name": "Saby_Должность",
    "raw": [
      "9",
      [
        "3"
      ],
      "0",
      "\"Saby_Должность\"",
      [
        "1",
        "1",
        [
          "\"ru\"",
          "\"Saby ФИО\""
        ]
      ],
      [
        "\"Pattern\"",
        [
          "\"S\"",
          "1",
          "1"
        ]
      ],
      [
        "0",
        [
          "0",
          [
            "\"B\"",
            "1"
          ],
          "0"
        ]
      ],
      [
        "0",
        [
          "0",
          [
            "\"B\"",
            "1"
          ],
          "0"
        ]
      ],
      [
        "0",
        "0"
      ],
      [
        "0",
        "0"
      ],
      "0",
      "0",
      "0",
      "0",
      [
        "0",
        "0"
      ],
      [
        "0",
        "0"
      ]
    ]
  },
  {
    "name": "Saby_ДействиеИнфо",
    "raw": [
      "9",
      [
        "4"
      ],
      "0",
      "\"Saby_ДействиеИнфо\"",
      [
        "1",
        "1",
        [
          "\"ru\"",
          "\"Saby действие инфо\""
        ]
      ],
      [
        "\"Pattern\"",
        [
          "\"S\"",
          "1",
          "1"
        ]
      ],
      [
        "0",
        [
          "0",
          [
            "\"B\"",
            "1"
          ],
          "0"
        ]
      ],
      [
        "0",
        [
          "0",
          [
            "\"B\"",
            "1"
          ],
          "0"
        ]
      ],
      [
        "0",
        "0"
      ],
      [
        "0",
        "0"
      ],
      "0",
      "0",
      "0",
      "0",
      [
        "0",
        "0"
      ],
      [
        "0",
        "0"
      ]
    ]
  },
  {
    "name": "Вложения",
    "raw": [
      "9",
      [
        "5"
      ],
      "0",
      "\"Вложения\"",
      [
        "1",
        "1",
        [
          "\"ru\"",
          "\"Вложения\""
        ]
      ],
      [
        "\"Pattern\"",
        [
          "\"#\"",
          "acf6192e-81ca-46ef-93a6-5a6968b78663"
        ]
      ],
      [
        "0",
        [
          "0",
          [
            "\"B\"",
            "1"
          ],
          "0"
        ]
      ],
      [
        "0",
        [
          "0",
          [
            "\"B\"",
            "1"
          ],
          "0"
        ]
      ],
      [
        "0",
        "0"
      ],
      [
        "0",
        "0"
      ],
      "0",
      "0",
      "0",
      "1",
      [
        "5",
        "1",
        "0",
        "\"НаименованиеВложения\"",
        [
          "1",
          "1",
          [
            "\"ru\"",
            "\"Файлы\""
          ]
        ],
        [
          "\"Pattern\"",
          [
            "\"S\""
          ]
        ],
        [
          "0",
          [
            "0",
            [
              "\"B\"",
              "1"
            ],
            "0"
          ]
        ],
        [
          "0",
          [
            "0",
            [
              "\"B\"",
              "1"
            ],
            "0"
          ]
        ],
        [
          "0",
          "0"
        ],
        "0"
      ],
      [
        "0",
        "0"
      ],
      [
        "0",
        "0"
      ]
    ]
  }
]